{
  "nodes": [
    {"id": "source", "capacity": 100},
    {"id": "constitution", "capacity": 50},
    {"id": "clarify", "capacity": 50},
    {"id": "specify", "capacity": 60},
    {"id": "plan", "capacity": 80},
    {"id": "tasks", "capacity": 70},
    {"id": "implement", "capacity": 90},
    {"id": "grok-x-insights", "capacity": 30},
    {"id": "sink", "capacity": 100}
  ],
  "edges": [
    {"from": "source", "to": "constitution", "weight": 1},
    {"from": "source", "to": "clarify", "weight": 1},
    {"from": "constitution", "to": "specify", "weight": 1},
    {"from": "clarify", "to": "specify", "weight": 1},
    {"from": "specify", "to": "plan", "weight": 1},
    {"from": "plan", "to": "tasks", "weight": 1},
    {"from": "tasks", "to": "implement", "weight": 1},
    {"from": "implement", "to": "sink", "weight": 1},
    {"from": "clarify", "to": "grok-x-insights", "weight": 1},
    {"from": "grok-x-insights", "to": "specify", "weight": 1}
  ]
}